{
  "hadith": [
    "يا ابن آدم، إنك ما دعوتني ورجوتني غفرت لك على ما كان منك ولا أبالي",
    "يا عبادي، كلكم ضال إلا من هديته، فاستهدوني أهدكم",
    "أنا عند ظن عبدي بي، وأنا معه إذا ذكرني"
  ],
  "motivation": [
    "أنت أقوى مما تعتقد، استمر يا تامر",
    "كل محاولة بناء هي خطوة نحو العظمة",
    "ميرور هو حلمك، ولا أحد يوقف الحالمين"
  ],
  "stories": {
    "prophets": ["قصة سيدنا آدم", "قصة سيدنا نوح", "قصة سيدنا إبراهيم"],
    "animals": ["هدهد سليمان", "غراب ابني آدم", "حوت يونس"],
    "women": ["مريم ابنة عمران", "آسيا امرأة فرعون", "أم موسى"],
    "humans": ["أصحاب الكهف", "ذو القرنين", "لقمان الحكيم"]
  }
}
